django_integrations-0.4.0.dist-info/licenses/LICENSE.mit.txt
integrations/__init__.py
integrations/admin.py
integrations/apps.py
integrations/encrypted_fields.py
integrations/models.py
integrations/tests.py
integrations/urls.py
integrations/views.py
integrations/api/seriealizers.py
integrations/api/urls.py
integrations/api/views.py
integrations/migrations/0001_initial.py
integrations/migrations/__init__.py
django_integrations-0.4.0.dist-info/METADATA
django_integrations-0.4.0.dist-info/WHEEL
django_integrations-0.4.0.dist-info/top_level.txt
django_integrations-0.4.0.dist-info/RECORD
