Metadata-Version: 2.4
Name: django-integrations
Version: 0.4.0
Summary: Tools for creating and managing multi-site integrations like API Keys and Tokens.
Author: Roberto Himmelbauer
Author-email: Grant Viklund <renderbox@gmail.com>
Project-URL: Homepage, https://github.com/renderbox/django-integrations
Project-URL: Bug Tracker, https://github.com/renderbox/django-integrations/issues
Keywords: django,app
Classifier: Intended Audience :: Developers
Classifier: Programming Language :: Python :: 3 :: Only
Classifier: Programming Language :: Python :: 3.10
Classifier: Programming Language :: Python :: 3.11
Classifier: Programming Language :: Python :: 3.12
Classifier: Programming Language :: Python :: 3.13
Requires-Python: >=3.10
License-File: LICENSE.mit.txt
Requires-Dist: Django<6.0,>=4.0
Requires-Dist: cryptography<46.0.0,>=45.0.2
Provides-Extra: dev
Requires-Dist: black; extra == "dev"
Requires-Dist: flake8; extra == "dev"
Requires-Dist: flake8-black; extra == "dev"
Requires-Dist: mypy; extra == "dev"
Requires-Dist: bandit; extra == "dev"
Requires-Dist: isort; extra == "dev"
Requires-Dist: dj-database-url; extra == "dev"
Requires-Dist: django-crispy-forms; extra == "dev"
Requires-Dist: django-allauth; extra == "dev"
Requires-Dist: django-extensions; extra == "dev"
Requires-Dist: psycopg2-binary; extra == "dev"
Provides-Extra: test
Requires-Dist: coverage; extra == "test"
Requires-Dist: pytest; extra == "test"
Requires-Dist: pytest-django; extra == "test"
Requires-Dist: dj-database-url; extra == "test"
Requires-Dist: django-crispy-forms; extra == "test"
Requires-Dist: django-allauth; extra == "test"
Requires-Dist: django-extensions; extra == "test"
Requires-Dist: psycopg2-binary; extra == "test"
Dynamic: license-file
